[
  {
    "name": "Wachalarm Nordwest",
    "landkreis": "Leitstelle Nordwest",
    "region": "Nordwest",
    "type": "hauptkanal",
    "lat": 52.9500,
    "lng": 12.1500,
    "url": "https://whatsapp.com/channel/0029VbCyfZN35fLvfxdCKJ3G",
    "description": "Aktuelle Feuerwehreinsätze aus dem Nordwesten Brandenburgs direkt per WhatsApp."
  },
  {
    "name": "Wachalarm Prignitz",
    "landkreis": "Prignitz",
    "kommune": "Prignitz",
    "ort": "Landkreis Prignitz",
    "typ": "Landkreis",
    "eviAlarmierung": true,
    "lat": 53.075,
    "lng": 11.858,
    "link": "https://whatsapp.com/channel/0029VbDEy0pGehETHpOZg00X"
  }
]
